micro_test_hub/__init__.py
micro_test_hub/platforms/IPlatform.py
micro_test_hub/platforms/docker_compose/DCPlatform.py
micro_test_hub/platforms/docker_compose/DockerComposePlatform.py
micro_test_hub/platforms/docker_compose/service_handlers/DockerHandler.py
micro_test_hub/platforms/docker_compose/service_handlers/FunctionHandler.py
micro_test_hub/platforms/docker_compose/service_handlers/PostgresHandler.py
micro_test_hub/platforms/docker_compose/service_handlers/TestHandler.py
micro_test_hub/platforms/docker_compose/service_handlers/gcp_services/FirestoreHandler.py
micro_test_hub/platforms/docker_compose/service_handlers/gcp_services/GCPServiceHandler.py
micro_test_hub/platforms/docker_compose/service_handlers/gcp_services/PubSubHandler.py
micro_test_hub/platforms/docker_compose/service_handlers/gcp_services/StorageHandler.py
micro_test_hub/platforms/docker_compose/service_handlers/gcp_services/StorageProxy.py
micro_test_hub/services/Service.py
micro_test_hub/test_suites/MicroTestProject.py
micro_test_hub/test_suites/MicroTestSuite.py
micro_test_hub/transports/__init__.py
micro_test_hub/transports/cli/__init__.py
micro_test_hub/transports/cli/v1_0/__init__.py
micro_test_hub/transports/cli/v1_0/commands/project_commands.py
micro_test_hub/transports/cli/v1_0/main.py
micro_test_hub-0.1.10.dist-info/METADATA
micro_test_hub-0.1.10.dist-info/WHEEL
micro_test_hub-0.1.10.dist-info/entry_points.txt
micro_test_hub-0.1.10.dist-info/RECORD
