Metadata-Version: 2.1
Name: micro_test_hub
Version: 0.1.10
Summary: A system to support the creation of integration tests for MOC microservices
Author: Damianos Damianidis
Requires-Python: >=3.10,<4.0
Classifier: Programming Language :: Python :: 3
Classifier: Programming Language :: Python :: 3.10
Classifier: Programming Language :: Python :: 3.11
Classifier: Programming Language :: Python :: 3.12
Requires-Dist: Click (==8.1.7)
Requires-Dist: gitpython (==3.1.43)
Requires-Dist: google-cloud-pubsub (==2.10.0)
Requires-Dist: pydantic (==2.7.4)
Requires-Dist: pyyaml (==6.0.1)
